{
	"$schema": "https://shadcn-svelte.com/schema/registry-item.json",
	"name": "square-arrow-down-right",
	"title": "square-arrow-down-right",
	"type": "registry:component",
	"description": "The animated square-arrow-down-right icon component.",
	"author": "jis3r <jis3r@protonmail.com>",
	"files": [
		{
			"type": "registry:component",
			"target": "~/src/lib/components/movingicons/square-arrow-down-right.svelte",
			"content": "<script lang=\"ts\">\n\timport type { IconProps } from './types.js';\n\n\tlet {\n\t\tcolor = 'currentColor',\n\t\tsize = 24,\n\t\tstrokeWidth = 2,\n\t\tanimate = false,\n\t\tclass: className = ''\n\t}: IconProps = $props();\n\n\tfunction handleMouseEnter() {\n\t\tif (animate) return;\n\t\tanimate = true;\n\t\tsetTimeout(() => {\n\t\t\tanimate = false;\n\t\t}, 200);\n\t}\n</script>\n\n<div\n\tclass={className}\n\taria-label=\"square-arrow-down-right\"\n\trole=\"img\"\n\tonmouseenter={handleMouseEnter}\n>\n\t<svg\n\t\txmlns=\"http://www.w3.org/2000/svg\"\n\t\twidth={size}\n\t\theight={size}\n\t\tviewBox=\"0 0 24 24\"\n\t\tfill=\"none\"\n\t\tstroke={color}\n\t\tstroke-width={strokeWidth}\n\t\tstroke-linecap=\"round\"\n\t\tstroke-linejoin=\"round\"\n\t>\n\t\t<rect width=\"18\" height=\"18\" x=\"3\" y=\"3\" rx=\"2\" />\n\t\t<path d=\"M16 8v8H8\" class:head={animate} />\n\t\t<path d=\"M16 16 L12 12\" class:head={animate} />\n\t\t<path d=\"M8 8 L12 12\" />\n\t</svg>\n</div>\n\n<style>\n\tdiv {\n\t\tdisplay: inline-block;\n\t}\n\tpath {\n\t\ttransition: all 0.2s ease-out;\n\t}\n\t.head {\n\t\ttransform: translate(-1.5px, -1.5px);\n\t}\n</style>\n"
		}
	],
	"registryDependencies": []
}
